odoo/addons/l10n_it_fatturapa_export_zip/README.rst
odoo/addons/l10n_it_fatturapa_export_zip/__init__.py
odoo/addons/l10n_it_fatturapa_export_zip/__manifest__.py
odoo/addons/l10n_it_fatturapa_export_zip/i18n/it.po
odoo/addons/l10n_it_fatturapa_export_zip/i18n/l10n_it_fatturapa_export_zip.pot
odoo/addons/l10n_it_fatturapa_export_zip/models/__init__.py
odoo/addons/l10n_it_fatturapa_export_zip/models/attachment.py
odoo/addons/l10n_it_fatturapa_export_zip/readme/CONTRIBUTORS.rst
odoo/addons/l10n_it_fatturapa_export_zip/readme/DESCRIPTION.rst
odoo/addons/l10n_it_fatturapa_export_zip/static/description/icon.png
odoo/addons/l10n_it_fatturapa_export_zip/static/description/index.html
odoo/addons/l10n_it_fatturapa_export_zip/views/attachment_view.xml
odoo/addons/l10n_it_fatturapa_export_zip/wizard/__init__.py
odoo/addons/l10n_it_fatturapa_export_zip/wizard/export_fatturapa.py
odoo/addons/l10n_it_fatturapa_export_zip/wizard/export_fatturapa_view.xml
odoo12_addon_l10n_it_fatturapa_export_zip-12.0.1.0.1.dist-info/METADATA
odoo12_addon_l10n_it_fatturapa_export_zip-12.0.1.0.1.dist-info/WHEEL
odoo12_addon_l10n_it_fatturapa_export_zip-12.0.1.0.1.dist-info/top_level.txt
odoo12_addon_l10n_it_fatturapa_export_zip-12.0.1.0.1.dist-info/RECORD
