Metadata-Version: 2.1
Name: odoo12-addon-l10n-it-fatturapa-export-zip
Version: 12.0.1.0.1
Summary: Permette di esportare in uno ZIP diversi file XML di fatture elettroniche
Home-page: https://github.com/OCA/l10n-italy
Author: Efatto.it di Sergio Corato, Odoo Community Association (OCA)
Author-email: support@odoo-community.org
License: AGPL-3
Platform: UNKNOWN
Classifier: Programming Language :: Python
Classifier: Framework :: Odoo
Classifier: License :: OSI Approved :: GNU Affero General Public License v3
Classifier: Development Status :: 4 - Beta
Requires-Python: >=3.5
Requires-Dist: odoo12-addon-l10n-it-fatturapa-in
Requires-Dist: odoo12-addon-l10n-it-fatturapa-out
Requires-Dist: odoo (<12.1dev,>=12.0a)
